libpixelair/__init__.py
libpixelair/_internal.py
libpixelair/_types.py
libpixelair/arp.py
libpixelair/device.py
libpixelair/discovery.py
libpixelair/packet_assembler.py
libpixelair/pixelairfb/PixelAir/Audio.py
libpixelair/pixelairfb/PixelAir/AutoMode.py
libpixelair/pixelairfb/PixelAir/BooleanParameter.py
libpixelair/pixelairfb/PixelAir/Clock.py
libpixelair/pixelairfb/PixelAir/Dashboard.py
libpixelair/pixelairfb/PixelAir/Engine.py
libpixelair/pixelairfb/PixelAir/FloatParameter.py
libpixelair/pixelairfb/PixelAir/IntParameter.py
libpixelair/pixelairfb/PixelAir/LightSensorSettings.py
libpixelair/pixelairfb/PixelAir/ManualMode.py
libpixelair/pixelairfb/PixelAir/Network.py
libpixelair/pixelairfb/PixelAir/Notification.py
libpixelair/pixelairfb/PixelAir/Notifications.py
libpixelair/pixelairfb/PixelAir/OTA.py
libpixelair/pixelairfb/PixelAir/Palette.py
libpixelair/pixelairfb/PixelAir/PixelAirDevice.py
libpixelair/pixelairfb/PixelAir/Scene.py
libpixelair/pixelairfb/PixelAir/SceneMode.py
libpixelair/pixelairfb/PixelAir/Schedule.py
libpixelair/pixelairfb/PixelAir/StringParameter.py
libpixelair/pixelairfb/PixelAir/Trigger.py
libpixelair/pixelairfb/PixelAir/__init__.py
libpixelair/pixelairfb/__init__.py
libpixelair/py.typed
libpixelair/udp_listener.py
libpixelair-1.0.0.dist-info/METADATA
libpixelair-1.0.0.dist-info/WHEEL
libpixelair-1.0.0.dist-info/entry_points.txt
libpixelair-1.0.0.dist-info/licenses/LICENSE
libpixelair-1.0.0.dist-info/RECORD
