Metadata-Version: 2.4
Name: libpixelair
Version: 1.0.0
Summary: Python client library for PixelAir LED devices (Fluora, Monos)
License: MIT
License-File: LICENSE
Keywords: pixelair,fluora,monos,led,home-assistant,iot
Author: Aiden Vigue
Author-email: aiden.vigue@koiosdigital.net
Requires-Python: >=3.12,<4.0
Classifier: Development Status :: 4 - Beta
Classifier: Intended Audience :: Developers
Classifier: License :: OSI Approved :: MIT License
Classifier: Operating System :: OS Independent
Classifier: Programming Language :: Python :: 3
Classifier: Programming Language :: Python :: 3.12
Classifier: Programming Language :: Python :: 3.13
Classifier: Programming Language :: Python :: 3.14
Classifier: Topic :: Home Automation
Classifier: Typing :: Typed
Requires-Dist: flatbuffers (>=25.2.10,<26.0.0)
Requires-Dist: netifaces (>=0.11.0,<0.12.0)
Requires-Dist: python-osc (>=1.8.3,<2.0.0)
Project-URL: Documentation, https://koios.github.io/libpixelair/
Project-URL: Repository, https://github.com/Koios/libpixelair
